sudorouter/__init__.py
sudorouter/http.py
sudorouter/httpx.py
sudorouter/quoter.py
sudorouter/tls.py
sudorouter/example/example_http.py
sudorouter/example/example_httpx.py
sudorouter/tdx/__init__.py
sudorouter/tdx/quote.py
sudorouter/tdx/verify.py
sudorouter-0.0.3.dist-info/METADATA
sudorouter-0.0.3.dist-info/WHEEL
sudorouter-0.0.3.dist-info/top_level.txt
sudorouter-0.0.3.dist-info/RECORD
