Metadata-Version: 2.4
Name: sudorouter
Version: 0.0.3
Summary: The official Python library for the SudoRouter
Author: SudoRouter
Project-URL: Homepage, https://sudorouter.ai
Classifier: Programming Language :: Python :: 3
Requires-Dist: httpx<1,>=0.27.0
Requires-Dist: urllib3
Requires-Dist: pyOpenSSL>=25.0.0
Requires-Dist: cryptography>=45.0.0
